pythbase/__init__.py
pythbase/pythbase.py
pythbase-0.0.1.dist-info/LICENSE
pythbase-0.0.1.dist-info/METADATA
pythbase-0.0.1.dist-info/WHEEL
pythbase-0.0.1.dist-info/top_level.txt
pythbase-0.0.1.dist-info/RECORD
