Metadata-Version: 2.1
Name: pythbase
Version: 0.0.1
Summary: Python connection pool for hbase
Home-page: https://github.com/shawjan/pythbase
Author: darrenfore
Author-email: darrenfore@gmail.com
License: UNKNOWN
Project-URL: Bug Tracker, https://github.com/shawjan/pythbase/issues
Platform: UNKNOWN
Classifier: Programming Language :: Python :: 3
Classifier: License :: OSI Approved :: MIT License
Classifier: Operating System :: OS Independent
Requires-Python: >=3.5
License-File: LICENSE
